django_splint/__init__.py
django_splint/admin.py
django_splint/task.py
django_splint/api/__init__.py
django_splint/api/authentication.py
django_splint/api/filters.py
django_splint/api/permissions.py
django_splint/api/serializers.py
django_splint/api/views.py
django_splint/db/__init__.py
django_splint/db/fields.py
django_splint/db/models.py
django_splint/utils/__init__.py
django_splint/utils/decorators.py
django_splint/utils/api/__init__.py
django_splint/utils/api/authentication.py
django_splint/utils/aws/__init__.py
django_splint/utils/aws/ecs.py
django_splint/utils/aws/sqs.py
django_splint/utils/aws/function/logging.py
django_splint/utils/google/__init__.py
django_splint/utils/google/firebase.py
django_splint_kovs-0.0.63.dist-info/METADATA
django_splint_kovs-0.0.63.dist-info/WHEEL
django_splint_kovs-0.0.63.dist-info/top_level.txt
django_splint_kovs-0.0.63.dist-info/RECORD
