Metadata-Version: 2.4
Name: django-splint-kovs
Version: 0.0.63
Summary: Simple package with utilities for projects with Django Framework
Author-email: Silvio Moreto <silvio.moreto@medway.com.br>
Project-URL: Homepage, https://github.com/medway-dev/django-splint-kovs
Classifier: Programming Language :: Python :: 3
Classifier: License :: OSI Approved :: MIT License
Classifier: Operating System :: OS Independent
Requires-Python: >=3.0
Requires-Dist: boto3>=1.13
Requires-Dist: django>=2.2.11
Requires-Dist: djangorestframework>=3.11.0
Requires-Dist: django-filter>=2.2.0
Requires-Dist: aws-lambda-powertools==2.4.0
Requires-Dist: firebase-admin<6.3,>=6.2
Requires-Dist: Pillow>=8.0.0
